{
  "name": "Commission Discrepancy Escalation (Template)",
  "nodes": [
    {
      "id": "c8bb8bc1-64a3-5f5e-a614-9b446378398c",
      "name": "Hourly Schedule",
      "type": "n8n-nodes-base.scheduleTrigger",
      "typeVersion": 1,
      "position": [
        240,
        300
      ],
      "parameters": {
        "rule": {
          "interval": [
            {
              "field": "hours",
              "hoursInterval": 1
            }
          ]
        }
      }
    },
    {
      "id": "18b7a7d1-f3c8-578c-8a0c-14cd3616837b",
      "name": "Fetch Records",
      "type": "n8n-nodes-base.httpRequest",
      "typeVersion": 1,
      "position": [
        460,
        300
      ],
      "parameters": {
        "method": "GET",
        "url": "https://api.example.com/sales-commission-discrepancy-escalation/list",
        "authentication": "genericCredentialType",
        "options": {},
        "sendBody": false,
        "bodyParameters": {}
      }
    },
    {
      "id": "5165d5db-631e-58d1-877e-b412188fe837",
      "name": "Aggregate Results",
      "type": "n8n-nodes-base.code",
      "typeVersion": 1,
      "position": [
        680,
        300
      ],
      "parameters": {
        "jsCode": "// Aggregate fetched records for Commission Discrepancy Escalation.\nconst items = $input.all();\nreturn items.map((it) => ({ json: { ...it.json, processed: true } }));\n",
        "mode": "runOnceForAllItems"
      }
    },
    {
      "id": "8d19c8a3-8231-550c-b4d5-ec3cd0fdde16",
      "name": "Has Results",
      "type": "n8n-nodes-base.if",
      "typeVersion": 1,
      "position": [
        900,
        300
      ],
      "parameters": {
        "conditions": {
          "string": [
            {
              "value1": "={{$json[\"count\"]}}",
              "operation": "largerEqual"
            }
          ]
        }
      }
    },
    {
      "id": "9712dde1-261b-5e47-a708-d2d983377680",
      "name": "Notify Channel",
      "type": "n8n-nodes-base.httpRequest",
      "typeVersion": 1,
      "position": [
        1120,
        200
      ],
      "parameters": {
        "method": "POST",
        "url": "https://api.example.com/sales-commission-discrepancy-escalation/notify",
        "authentication": "genericCredentialType",
        "options": {},
        "sendBody": true,
        "bodyParameters": {
          "parameters": [
            {
              "name": "placeholder",
              "value": "REPLACE_WITH_YOUR_VALUE"
            }
          ]
        }
      }
    },
    {
      "id": "3d9e2715-f107-58ba-9542-b7963468a8ad",
      "name": "No Work",
      "type": "n8n-nodes-base.noOp",
      "typeVersion": 1,
      "position": [
        1120,
        420
      ],
      "parameters": {}
    }
  ],
  "connections": {
    "Hourly Schedule": {
      "main": [
        [
          {
            "node": "Fetch Records",
            "type": "main",
            "index": 0
          }
        ]
      ]
    },
    "Fetch Records": {
      "main": [
        [
          {
            "node": "Aggregate Results",
            "type": "main",
            "index": 0
          }
        ]
      ]
    },
    "Aggregate Results": {
      "main": [
        [
          {
            "node": "Has Results",
            "type": "main",
            "index": 0
          }
        ]
      ]
    },
    "Has Results": {
      "main": [
        [
          {
            "node": "Notify Channel",
            "type": "main",
            "index": 0
          }
        ],
        [
          {
            "node": "No Work",
            "type": "main",
            "index": 0
          }
        ]
      ]
    }
  },
  "settings": {
    "executionOrder": "v1"
  },
  "active": false,
  "tags": [
    {
      "name": "category:sales"
    },
    {
      "name": "pattern:schedule-fetch-aggregate"
    },
    {
      "name": "expansion-pack-v0"
    }
  ],
  "meta": {
    "templateGenerator": "open-workflow-library-expansion-pack-v0",
    "templateCategory": "sales",
    "templatePattern": "schedule-fetch-aggregate"
  },
  "versionId": "35b67056-c422-5485-99e1-2ffb39b0fa89",
  "id": "e6a99ace-3353-5dc6-a55d-09e4bc37c00d"
}