{
  "name": "Weekly Campaign Digest (Template)",
  "nodes": [
    {
      "id": "cbdc59e5-3137-5258-b85a-905a515e2417",
      "name": "Manual Trigger",
      "type": "n8n-nodes-base.manualTrigger",
      "typeVersion": 1,
      "position": [
        240,
        300
      ],
      "parameters": {}
    },
    {
      "id": "b73be8b3-1d29-5d13-8f01-669a8ed4d2ae",
      "name": "Sample Input",
      "type": "n8n-nodes-base.set",
      "typeVersion": 1,
      "position": [
        460,
        300
      ],
      "parameters": {
        "keepOnlySet": false,
        "values": {
          "string": [
            {
              "name": "subject",
              "value": "Weekly Campaign Digest"
            },
            {
              "name": "ref",
              "value": "REPLACE_WITH_YOUR_VALUE"
            }
          ]
        },
        "options": {}
      }
    },
    {
      "id": "ac858b23-8c58-5691-8279-9400966b6af0",
      "name": "Lookup External",
      "type": "n8n-nodes-base.httpRequest",
      "typeVersion": 1,
      "position": [
        680,
        300
      ],
      "parameters": {
        "method": "GET",
        "url": "https://api.example.com/marketing-weekly-campaign-digest/lookup",
        "authentication": "genericCredentialType",
        "options": {},
        "sendBody": false,
        "bodyParameters": {}
      }
    },
    {
      "id": "df2bf8a4-0c8f-5b93-b82b-86ba6d765320",
      "name": "Transform Payload",
      "type": "n8n-nodes-base.code",
      "typeVersion": 1,
      "position": [
        900,
        300
      ],
      "parameters": {
        "jsCode": "// Transform lookup result for Weekly Campaign Digest.\nconst items = $input.all();\nreturn items.map((it) => ({ json: { ...it.json, processed: true } }));\n",
        "mode": "runOnceForAllItems"
      }
    },
    {
      "id": "45a36f87-5e37-5643-970c-d890beeacef2",
      "name": "Store Record",
      "type": "n8n-nodes-base.httpRequest",
      "typeVersion": 1,
      "position": [
        1120,
        300
      ],
      "parameters": {
        "method": "POST",
        "url": "https://api.example.com/marketing-weekly-campaign-digest/store",
        "authentication": "genericCredentialType",
        "options": {},
        "sendBody": true,
        "bodyParameters": {
          "parameters": [
            {
              "name": "placeholder",
              "value": "REPLACE_WITH_YOUR_VALUE"
            }
          ]
        }
      }
    },
    {
      "id": "a59149dd-d45b-5f18-89c9-117ffaa2a429",
      "name": "Done",
      "type": "n8n-nodes-base.noOp",
      "typeVersion": 1,
      "position": [
        1340,
        300
      ],
      "parameters": {}
    }
  ],
  "connections": {
    "Manual Trigger": {
      "main": [
        [
          {
            "node": "Sample Input",
            "type": "main",
            "index": 0
          }
        ]
      ]
    },
    "Sample Input": {
      "main": [
        [
          {
            "node": "Lookup External",
            "type": "main",
            "index": 0
          }
        ]
      ]
    },
    "Lookup External": {
      "main": [
        [
          {
            "node": "Transform Payload",
            "type": "main",
            "index": 0
          }
        ]
      ]
    },
    "Transform Payload": {
      "main": [
        [
          {
            "node": "Store Record",
            "type": "main",
            "index": 0
          }
        ]
      ]
    },
    "Store Record": {
      "main": [
        [
          {
            "node": "Done",
            "type": "main",
            "index": 0
          }
        ]
      ]
    }
  },
  "settings": {
    "executionOrder": "v1"
  },
  "active": false,
  "tags": [
    {
      "name": "category:marketing"
    },
    {
      "name": "pattern:manual-sample-transform-store"
    },
    {
      "name": "expansion-pack-v0"
    }
  ],
  "meta": {
    "templateGenerator": "open-workflow-library-expansion-pack-v0",
    "templateCategory": "marketing",
    "templatePattern": "manual-sample-transform-store"
  },
  "versionId": "375aa4eb-af6c-58e9-9cbb-6a9bb36565db",
  "id": "65b34356-0aa8-58a4-a168-722b8f960182"
}